infini_gram-2.6.0.dist-info/RECORD
infini_gram-2.6.0.dist-info/WHEEL
infini_gram-2.6.0.dist-info/top_level.txt
infini_gram-2.6.0.dist-info/METADATA
infini_gram/cpp_engine.cpython-312-darwin.so
infini_gram/models.py
infini_gram/indexing_v6.py
infini_gram/cpp_engine.cpp
infini_gram/__init__.py
infini_gram/engine.py
infini_gram/py.typed
infini_gram/indexing.py
infini_gram/rust_indexing
