Metadata-Version: 2.4
Name: infini-gram
Version: 2.6.0
Summary: A Python package for infini-gram
Author: Jiacheng Liu
Author-email: liujc@cs.washington.edu
License: Apache 2.0
Requires-Python: >=3.11
Requires-Dist: tqdm
Dynamic: author
Dynamic: author-email
Dynamic: description
Dynamic: description-content-type
Dynamic: license
Dynamic: requires-dist
Dynamic: requires-python
Dynamic: summary
